latex_superfence.py
latex_superfence-0.0.12.dist-info/COPYING
latex_superfence-0.0.12.dist-info/METADATA
latex_superfence-0.0.12.dist-info/WHEEL
latex_superfence-0.0.12.dist-info/top_level.txt
latex_superfence-0.0.12.dist-info/RECORD
